{
    "name": "HPE(BOM)",
    "children": [{"name": "1A1E", "children": [{"name": "R0J68A", "children": [{"name": "416151-B21", "children": [{"name": "142263-001", "children": [{"name": "", "children": [{"name": ""}]}]}]}, {"name": "416454-B21", "children": [{"name": "142263-008", "children": [{"name": "", "children": [{"name": ""}]}]}]}, {"name": "652239-B21", "children": [{"name": "652240-001", "children": [{"name": "", "children": [{"name": ""}]}]}]}, {"name": "654961-B21", "children": [{"name": "652999-001", "children": [{"name": "", "children": [{"name": ""}]}]}]}, {"name": "696627-B21", "children": [{"name": "", "children": [{"name": "", "children": [{"name": ""}]}]}]}, {"name": "723597-B21", "children": [{"name": "723594-001", "children": [{"name": "723595-501", "children": [{"name": ""}]}, {"name": "723595-101", "children": [{"name": ""}]}, {"name": "723595-201", "children": [{"name": ""}]}]}]}, {"name": "726737-B21", "children": [{"name": "726738-001", "children": [{"name": "", "children": [{"name": ""}]}]}]}, {"name": "727259-B21", "children": [{"name": "876850-001", "children": [{"name": "", "children": [{"name": ""}]}]}]}, {"name": "729842-002", "children": [{"name": "", "children": [{"name": "", "children": [{"name": ""}]}]}]}, {"name": "729842-003", "children": [{"name": "", "children": [{"name": "", "children": [{"name": ""}]}]}]}, {"name": "734806-B21", "children": [{"name": "728440-002", "children": [{"name": "", "children": [{"name": ""}]}]}]}, {"name": "750678-001", "children": [{"name": "743454-001", "children": [{"name": "", "children": [{"name": ""}]}]}, {"name": "750688-001", "children": [{"name": "792851-001", "children": [{"name": ""}]}, {"name": "792852-001", "children": [{"name": ""}]}]}]}, {"name": "753220-B21", "children": [{"name": "752368-081", "children": [{"name": "", "children": [{"name": ""}]}]}]}, {"name": "756907-001", "children": [{"name": "", "children": [{"name": "", "children": [{"name": ""}]}]}]}, {"name": "759515-001", "children": [{"name": "", "children": [{"name": "", "children": [{"name": ""}]}]}]}, {"name": "764631-B21", "children": [{"name": "", "children": [{"name": "", "children": [{"name": ""}]}]}]}, {"name": "811041-B21", "children": [{"name": "734042-001", "children": [{"name": "", "children": [{"name": ""}]}]}]}, {"name": "837630-B21", "children": [{"name": "729842-002", "children": [{"name": "", "children": [{"name": ""}]}]}, {"name": "729842-003", "children": [{"name": "", "children": [{"name": ""}]}]}, {"name": "750678-001", "children": [{"name": "750688-001", "children": [{"name": "792851-001"}, {"name": "792852-001"}]}, {"name": "743454-001", "children": [{"name": ""}]}]}, {"name": "756907-001", "children": [{"name": "", "children": [{"name": ""}]}]}]}, {"name": "872476-B21", "children": [{"name": "872483-001", "children": [{"name": "651687-001", "children": [{"name": ""}]}, {"name": "872483-002", "children": [{"name": ""}]}]}]}, {"name": "P00494-B21", "children": [{"name": "871708-B22", "children": [{"name": "", "children": [{"name": ""}]}]}]}, {"name": "P10380-D61", "children": [{"name": "", "children": [{"name": "", "children": [{"name": ""}]}]}]}]}]}, {"name": "1B1E", "children": [{"name": "R0J68A", "children": [{"name": "416151-B21", "children": [{"name": "142263-001", "children": [{"name": "", "children": [{"name": ""}]}]}]}, {"name": "416454-B21", "children": [{"name": "142263-008", "children": [{"name": "", "children": [{"name": ""}]}]}]}, {"name": "652239-B21", "children": [{"name": "652240-001", "children": [{"name": "", "children": [{"name": ""}]}]}]}, {"name": "654961-B21", "children": [{"name": "652999-001", "children": [{"name": "", "children": [{"name": ""}]}]}]}, {"name": "696627-B21", "children": [{"name": "", "children": [{"name": "", "children": [{"name": ""}]}]}]}, {"name": "723597-B21", "children": [{"name": "723594-001", "children": [{"name": "723595-501", "children": [{"name": ""}]}, {"name": "723595-201", "children": [{"name": ""}]}, {"name": "723595-101", "children": [{"name": ""}]}]}]}, {"name": "726737-B21", "children": [{"name": "726738-001", "children": [{"name": "", "children": [{"name": ""}]}]}]}, {"name": "727259-B21", "children": [{"name": "876850-001", "children": [{"name": "", "children": [{"name": ""}]}]}]}, {"name": "729842-002", "children": [{"name": "", "children": [{"name": "", "children": [{"name": ""}]}]}]}, {"name": "729842-003", "children": [{"name": "", "children": [{"name": "", "children": [{"name": ""}]}]}]}, {"name": "734806-B21", "children": [{"name": "728440-002", "children": [{"name": "", "children": [{"name": ""}]}]}]}, {"name": "750678-001", "children": [{"name": "743454-001", "children": [{"name": "", "children": [{"name": ""}]}]}, {"name": "750688-001", "children": [{"name": "792851-001", "children": [{"name": ""}]}, {"name": "792852-001", "children": [{"name": ""}]}]}]}, {"name": "753220-B21", "children": [{"name": "752368-081", "children": [{"name": "", "children": [{"name": ""}]}]}]}, {"name": "756907-001", "children": [{"name": "", "children": [{"name": "", "children": [{"name": ""}]}]}]}, {"name": "759515-001", "children": [{"name": "", "children": [{"name": "", "children": [{"name": ""}]}]}]}, {"name": "764631-B21", "children": [{"name": "", "children": [{"name": "", "children": [{"name": ""}]}]}]}, {"name": "811041-B21", "children": [{"name": "734042-001", "children": [{"name": "", "children": [{"name": ""}]}]}]}, {"name": "837630-B21", "children": [{"name": "729842-002", "children": [{"name": "", "children": [{"name": ""}]}]}, {"name": "729842-003", "children": [{"name": "", "children": [{"name": ""}]}]}, {"name": "750678-001", "children": [{"name": "743454-001", "children": [{"name": ""}]}, {"name": "750688-001", "children": [{"name": "792852-001"}, {"name": "792851-001"}]}]}, {"name": "756907-001", "children": [{"name": "", "children": [{"name": ""}]}]}]}, {"name": "872476-B21", "children": [{"name": "872483-001", "children": [{"name": "651687-001", "children": [{"name": ""}]}, {"name": "872483-002", "children": [{"name": ""}]}]}]}, {"name": "P00494-B21", "children": [{"name": "871708-B22", "children": [{"name": "", "children": [{"name": ""}]}]}]}, {"name": "P10380-D61", "children": [{"name": "", "children": [{"name": "", "children": [{"name": ""}]}]}]}]}]}]
}


